pointlessutils/__init__.py
pointlessutils/decorators.py
pointlessutils-0.1.5.dist-info/LICENSE
pointlessutils-0.1.5.dist-info/WHEEL
pointlessutils-0.1.5.dist-info/METADATA
pointlessutils-0.1.5.dist-info/RECORD
