Metadata-Version: 2.1
Name: pointlessutils
Version: 0.1.5
Summary: Pointless utilities for python.
Home-page: https://github.com/vcokltfre/pointlessutils
License: MIT
Author: vcokltfre
Author-email: vcokltfre@gmail.com
Requires-Python: >=3.8,<4.0
Classifier: License :: OSI Approved :: MIT License
Classifier: Programming Language :: Python :: 3
Classifier: Programming Language :: Python :: 3.8
Classifier: Programming Language :: Python :: 3.9
Project-URL: Repository, https://github.com/vcokltfre/pointlessutils
